{"hash":"f34fd2c444a074f4e0e67d525015a008ef8e766f","data":{"entry":{"id":"23859298304-1001075660570","title":"Php разработчик","text":"#вакансия #fullstack #СПб #Санкт-Петербург #office #PHP #JavaScript\nГород: Санкт-Петербург (ст.метро Чернышевская)\nКомпания: Innoscripta GmbH\nПозиция: Full-stack разработчик\nФормат работы: Офис\nЗанятость: полная\nЗарплатная вилка: 120 000 – 250 000 руб на руки \n\nInnoscripta GmbH занимается поиском и продвижением передовых научных технологий на рынке Германии. Сейчас компания ищет middle/senior full-stack разработчиков в новый офис в Санкт-Петербурге для разработки собственных IT-продуктов. Флагманский проект – разработка внутренней CRM-системы. \n\nСтек: PHP/Laravel, JavaScript/React.js, MySQL, Elasticsearch, MongoDB \n\nТребования:\n- Опыт коммерческой разработки от 3-х лет\n- Владение разговорным английским\n- Высокий уровень самостоятельности\n- Уверенное знание указанных технологий \n\nУсловия:\n- Официальное оформление по ТК РФ\n- График 5/2, плавающее начало дня (с 8:00 до 10:00)\n- Работа в одной из крупнейших инновационных компаний Германии\n- Командировки в Мюнхен или релокация через полгода работы\n- Возможность осваивать новые направления разработки\n\nКонтакты: career@innoscripta.com","markup":[{"type":"hashtag","offset":0,"length":9,"data":"вакансия"},{"type":"hashtag","offset":10,"length":10,"data":"fullstack"},{"type":"hashtag","offset":21,"length":4,"data":"СПб"},{"type":"hashtag","offset":26,"length":6,"data":"Санкт"},{"type":"hashtag","offset":43,"length":7,"data":"office"},{"type":"hashtag","offset":51,"length":4,"data":"PHP"},{"type":"hashtag","offset":56,"length":11,"data":"JavaScript"},{"type":"link","offset":1072,"length":22,"data":"mailto:career@innoscripta.com"}],"date":"2020-03-23T06:32:47+00:00","link":"tg://resolve?domain=php_jobs&post=0","tags":[{"name":"php"},{"name":"javascript"},{"name":"laravel"},{"name":"reactjs"},{"name":"mysql"},{"name":"elasticsearch"},{"name":"mongodb"}],"cities":[{"code":"munich","ruName":"Мюнхен","enName":"Munich","country":{"code":"germany","ruName":"Германия","enName":"Germany"}}],"allowsRemote":false}},"context":{"recordId":"23859298304-1001075660570","tags":["php","javascript","laravel","reactjs","mysql","elasticsearch","mongodb"]}}