{"hash":"f34fd2c444a074f4e0e67d525015a008ef8e766f","data":{"entry":{"id":"66416803840-1001054966032","title":"Android разработчик","text":"#вакансия #Moscow #fulltime #react #reactnative #senior\n\n✅Вакансия: React Native Senior dev\n✅Город: Москва \n✅ЗП: 200К - 250K net (рассмотрим ваши ожидания)\n✅Занятость: полная/ офис \n✅Компания: Нью Мед Солюшнс_ibolit.pro\n\n💥ibolit.pro– российская телемедицинская платформа, помогающая врачам и пациентам оставаться на связи в любой точке мира. Если вы хотите развиваться в перспективном направлении телемедицины, заниматься настоящими делами и сутью (никакой бюрократии и лишних согласований) и хотите получить разносторонний опыт – мы ждем Вас! \n❗️Сейчас мы ищем ведущего разработчика мобильных приложений, построенных на базе фреймворка React Native.\n\n👆Задачи:\nВам предстоит развивать мобильные приложения для докторов и пациентов, предоставляющих коммуникационные телемедицинские сервисы (чаты, видеоконференции), функционал работы с медицинской картой, записью на приемы и другие медицинские сервисы.\n\n👍Что мы готовы предложить:\n• «белоснежные» условия по оформлению;\n• достойная заработная плата;\n• ДМС;\n• бюджет на обучение и посещение конференций;\n• гибкий график;\n• комфортный офис в центре Москвы;\n• мы всегда приветствуем инициативу!\n\n👀Наши ожидания:\n• отличные знания React-стека;\n• отличное знание фреймворка React Native;\n• обязательным является наличие навыков нативной разработки мобильных приложений хотя бы для одной из плафторм - iOS(Swift) или Android(Kotlin).\n\n🤝Контакты: @Kate_Guseva","markup":[{"type":"hashtag","offset":0,"length":9,"data":"вакансия"},{"type":"hashtag","offset":10,"length":7,"data":"Moscow"},{"type":"hashtag","offset":18,"length":9,"data":"fulltime"},{"type":"hashtag","offset":28,"length":6,"data":"react"},{"type":"hashtag","offset":35,"length":12,"data":"reactnative"},{"type":"hashtag","offset":48,"length":7,"data":"senior"},{"type":"handle","offset":1395,"length":12,"data":"Kate_Guseva"}],"date":"2020-04-10T11:15:40+00:00","link":"tg://resolve?domain=mobile_jobs&post=63340","tags":[{"name":"mobile"},{"name":"android"},{"name":"ios"},{"name":"reactjs"},{"name":"dotnet"},{"name":"swift"},{"name":"kotlin"},{"name":"react-native"}],"cities":[{"code":"moscow","ruName":"Москва","enName":"Moscow","country":{"code":"russia","ruName":"Россия","enName":"Russia"}}],"allowsRemote":false}},"context":{"recordId":"66416803840-1001054966032","tags":["mobile","android","ios","reactjs","dotnet","swift","kotlin","react-native"]}}