{"hash":"f5f6bf98bd95e769321482904cbbd488f77922fd","data":{"entry":{"id":"103633911808-1001089317451","title":"Qa инженер","text":"#москва #тестировщик  #удаленно #вакансия\n\nПривет, Я – Алёна из \"Сберлогистика\",  мы логистический оператор федерального масштаба, развиваем собственную складскую инфраструктуру, курьерскую доставку и сеть пунктов выдачи заказов во всех регионах РФ. Наш основной продукт это логистическая платформа (Back + разные клиентские приложения, которые общаются с ним), позволяющая нашим пользователям оформлять, отправлять, отслеживать различные отправления, а нашим сотрудникам осуществлять всю логистику. Есть проекты как web так и mob для внутренних нужд и отдельных клиентов.\nРасширяем команду, ищем Тестировщика (ручное тестирование)\n👍Формат работы: 5/2, удалёнка, официальное оформление в штат Компании\n💵Вилка до 160 к gross \n\n❗️Что для нас важно?\n-Опыт тестирования web приложений и API, написания тестовой документации\n-Знание техник тест-дизайна \n-Опыт работы с БД \n-Опыт работы с системами логирования \n-Опыт работы с очередями \n-Понимание принципов клиент-серверной архитектуры, сетевых протоколов, HTTP протокола\n-Опыт работы с HTTP-клиентами (postman, сurl и т.п.)\n\n✅ Задачи:\n-Участие в формировании методик и процессов тестирования на проекте\n-Составление тестовой документации, ревью документации составленной другими тестировщиками \n-Тестирование продуктов компании\n-Взаимодействие с командой автоматизации  \n\n💚Расскажу подробности в лс: @yagodaalena","markup":[{"type":"hashtag","offset":0,"length":7,"data":"москва"},{"type":"hashtag","offset":8,"length":12,"data":"тестировщик"},{"type":"hashtag","offset":22,"length":9,"data":"удаленно"},{"type":"hashtag","offset":32,"length":9,"data":"вакансия"},{"type":"handle","offset":1350,"length":12,"data":"yagodaalena"}],"date":"2020-06-24T13:11:36+00:00","link":"tg://resolve?domain=qa_jobs&post=98833","tags":[{"name":"qa"},{"name":"web"}],"cities":[{"code":"moscow","ruName":"Москва","enName":"Moscow","country":{"code":"russia","ruName":"Россия","enName":"Russia"}}],"allowsRemote":true}},"context":{"recordId":"103633911808-1001089317451"}}