{"hash":"f5f6bf98bd95e769321482904cbbd488f77922fd","data":{"entry":{"id":"102940803072-1001089317451","title":"Qa инженер","text":"#QAинженервакансия #QAjava #автотестыjava #QAМосква #вакансияМосква #middle \nДобрый день! В настоящий момент нахожусь в поисках QА-инженера для международной аутсорсинговой компании на проект банковской сферы.\nМестоположение: Москва, м. Кутузовская, либо Нагатинская\nОплата труда: 130-160.000 рублей\nФункциональные задачи;\n•  Анализ требований\n•  Разработка автотестов на Java + Selenium\n•  Актуализация автотестов\n•  Анализ ошибок\n•  Формирование отчетов\nТребования:\n•  Опыт разработки на Java + Selenium от 2-х лет\n•  Знание инструмента Maven\n•  Знание Junit и Allure\n•  Знание XML\n•  Знание SQL (MS SQL, Oracle)\n•  Опыт работы с Git, JenkinS\n•  Опыт работы с Bug Tracking Systems (Jira, Redmine)\n•  Опыт работы с линейкой HP ALM\n•  Знание BDD (Cucumber)\nУсловия:\n•  Конкурентная заработная плата\n•  Оформление в соответствии с ТК РФ, соц. пакет\n•  Работа в команде профессионалов\n•  Обучение, наставничество в процессе работы\nБуду рада ответить на Ваши вопросы: @LyKatrin, ekaterina706712@mail.ru\n\n•","markup":[{"type":"hashtag","offset":0,"length":18,"data":"QAинженервакансия"},{"type":"hashtag","offset":19,"length":7,"data":"QAjava"},{"type":"hashtag","offset":27,"length":14,"data":"автотестыjava"},{"type":"hashtag","offset":42,"length":9,"data":"QAМосква"},{"type":"hashtag","offset":52,"length":15,"data":"вакансияМосква"},{"type":"hashtag","offset":68,"length":7,"data":"middle"},{"type":"handle","offset":965,"length":9,"data":"LyKatrin"},{"type":"link","offset":976,"length":23,"data":"mailto:ekaterina706712@mail.ru"}],"date":"2020-06-16T09:14:53+00:00","link":"tg://resolve?domain=qa_jobs&post=0","tags":[{"name":"qa"},{"name":"java"},{"name":"selenium"},{"name":"maven"},{"name":"junit"},{"name":"xml"},{"name":"sql"},{"name":"oracle"},{"name":"git"},{"name":"jenkins"},{"name":"cucumber"}],"cities":[{"code":"moscow","ruName":"Москва","enName":"Moscow","country":{"code":"russia","ruName":"Россия","enName":"Russia"}}],"allowsRemote":false}},"context":{"recordId":"102940803072-1001089317451"}}