{"hash":"f5f6bf98bd95e769321482904cbbd488f77922fd","data":{"entry":{"id":"71887224832-1001054966032","title":"Ios developer","text":"#вакансия #спб #ios #middle #senior #spb #офис #IoT #умныйдом \nMiddle/Senior iOS developer \nReady for Sky 🚀 \nhttps://readyforsky.com/ru/career/ \n📍 полный день, удаленно/офис (сейчас вся компания работает удаленно) \nМы ищем iOS developer, который будет разрабатывать приложение, использующее данные с IoT-устройств для предоставления пользователям нужных товаров и услуг \n💡 Используем: Swift, Objective-C; Jenkins; GraphQL; RxSwift; MVC, MVVM и Viper \nВ команде: разрабатываем новый функционал приложения, внутренние фреймворки (Private pods), фреймворки для общего доступа; пишем Unit тесты; принимаем участие в создании протоколов работы с умными устройствами; Refactoring и Code-review. \nПредлагаем: \nРаботу в профессиональной команде (team lead, senior, middle), более 300 000 активных пользователей приложения. \nПолностью белую ЗП от 130 до 250 тыс. руб. на руки \nПосле исп.срока корпоративный английский \n📬 Пиши: @Rupeka_Natali","markup":[{"type":"hashtag","offset":0,"length":9,"data":"вакансия"},{"type":"hashtag","offset":10,"length":4,"data":"спб"},{"type":"hashtag","offset":15,"length":4,"data":"ios"},{"type":"hashtag","offset":20,"length":7,"data":"middle"},{"type":"hashtag","offset":28,"length":7,"data":"senior"},{"type":"hashtag","offset":36,"length":4,"data":"spb"},{"type":"hashtag","offset":41,"length":5,"data":"офис"},{"type":"hashtag","offset":47,"length":4,"data":"IoT"},{"type":"hashtag","offset":52,"length":9,"data":"умныйдом"},{"type":"bold","offset":63,"length":27,"data":""},{"type":"bold","offset":92,"length":13,"data":""},{"type":"link","offset":110,"length":34,"data":"https://readyforsky.com/ru/career/"},{"type":"bold","offset":225,"length":13,"data":""},{"type":"bold","offset":376,"length":11,"data":""},{"type":"bold","offset":454,"length":10,"data":""},{"type":"bold","offset":693,"length":11,"data":""},{"type":"bold","offset":916,"length":5,"data":""},{"type":"handle","offset":922,"length":14,"data":"Rupeka_Natali"}],"date":"2020-06-23T16:01:18+00:00","link":"tg://resolve?domain=mobile_jobs&post=68557","tags":[{"name":"mobile"},{"name":"ios"},{"name":"swift"},{"name":"objective-c"},{"name":"jenkins"},{"name":"graphql"},{"name":"mvvm"}],"cities":[],"allowsRemote":true}},"context":{"recordId":"71887224832-1001054966032"}}