{"hash":"f5f6bf98bd95e769321482904cbbd488f77922fd","data":{"records":{"id":"hive","name":"hive","belongsTo":{"totalCount":3,"pageInfo":{"totalPages":1,"currentPage":1},"edges":[{"node":{"__typename":"Job","id":"1744830464-1001091028994","title":"Java разработчик","text":"#москва #вакансия #java #javateamlead \nВакансия: Lead/Senior java разработчик \nВилка заработной платы: 180 000 – 250 000 net\nФормат: офис\n\nПроекты по созданию/развитию информационных систем в части цифровизации городских сервисов ЖКХ.\nРабота с IoT-системами, проекты по Bigdata, сбору и анализу данных с множества источников.\n\n🔸Мы предлагаем:\n-Высокая заработная плата от 180 000 до 250 000 на руки;\n-Повышение ставки после испытательного срока;\n-13-я зарплата+премии по итогу выполнения проектов;\n-Полностью официальное оформление по ТК РФ;\n\n🔸Требования:\n-Опыт управления командой 6+ человек от 1-го года;\n-Базовые знания Computer Science (алгоритмы, структуры данных);\n-Опыт разработки серверной части приложений на Java;\n-Знание практик и инструментария DevOps;\n-Отличное знание Java 8+ и популярных библиотек (Log4J, Apache Commons, Google Guava);\n-Знание Linux, основы Shell scripts, понимание архитектуры ОС.\n\n🔸Стек технологий:\n-На проектах используются языки: Java, JavaScript(React + Redux);\n-Java-стэк: Java8, Spring, Spring Cloud, Apache Kafka, Apache Spark, Tomcat;\n-Docker, Postgres, HDFS, Apache Hive;\n-Gitlab, Telegram.\n\nКонтакт: @Zarnica_hr","markup":[{"type":"hashtag","offset":0,"length":7,"data":"москва"},{"type":"hashtag","offset":8,"length":9,"data":"вакансия"},{"type":"hashtag","offset":18,"length":5,"data":"java"},{"type":"hashtag","offset":24,"length":13,"data":"javateamlead"},{"type":"handle","offset":1147,"length":11,"data":"Zarnica_hr"}],"date":"2020-06-26T12:01:03+00:00","link":"tg://resolve?domain=jvmjobs&post=1664","tags":[{"name":"java"},{"name":"jvm"},{"name":"dotnet"},{"name":"apache"},{"name":"linux"},{"name":"shell"},{"name":"javascript"},{"name":"reactjs"},{"name":"redux"},{"name":"spring"},{"name":"cloud"},{"name":"kafka"},{"name":"tomcat"},{"name":"docker"},{"name":"postgresql"},{"name":"hdfs"},{"name":"hive"},{"name":"gitlab"},{"name":"react-redux"},{"name":"apache-spark"}],"cities":[{"code":"moscow"}],"allowsRemote":false}},{"node":{"__typename":"Job","id":"103208189952-1001089317451","title":"Qa инженер","text":"#fulltime #hadoop #sql #english #вакансия #QA #тестировщик \n#etl #Самара #офис #полнаязанятость \nЗаработная плата: от 80 000 (gross)\nВакансия: QA Engineer/QA Analyst (в трудовой книжке: Главный инженер)\nКомпания: ПАО Сбербанк, Адрес: ул. Ленина, д. 17 (м. Алабинское)\nПроект: Разработка Корпоративной Модели Данных\nЧто используем: Jenkins, Confluence, Jira, Hadoop, Excel, Hive, Impala, Spark, SQL, Agile (Sbergile), и др.\nЗадачи: \n - Разработка тестовых сценариев\n - Разработка и анализ документации\n - Развитие подходов к тестированию, организация тестирования\nТребования:\n - Высшее техническое\\математическое образование\n - Знание методик тестирования баз данных\n - Английский (документация и проектные курсы на англ.)\nУсловия:                                                                                 \n - Цифровая библиотека, digital-курсы, подписка на O'Reilly 35000+ книг\n - В пятницу работаем на час меньше                                                 \n - Свободный дресс-код\n - Премии\nЭтапы собеседований (онлайн): \n1. Команда смотрит резюме \n2. Zoom с представителем команды (до 30 минут)\n3. Zoom с руководителем (до 1 часа)\nОтзыв в течении 3-х бизнес дней \n\nОбращение в л/с @bogdanova_hr и резюме присылать на nsboykova@sberbank.ru","markup":[{"type":"hashtag","offset":0,"length":9,"data":"fulltime"},{"type":"hashtag","offset":10,"length":7,"data":"hadoop"},{"type":"hashtag","offset":18,"length":4,"data":"sql"},{"type":"hashtag","offset":23,"length":8,"data":"english"},{"type":"hashtag","offset":32,"length":9,"data":"вакансия"},{"type":"hashtag","offset":42,"length":3,"data":"QA"},{"type":"hashtag","offset":46,"length":12,"data":"тестировщик"},{"type":"hashtag","offset":60,"length":4,"data":"etl"},{"type":"hashtag","offset":65,"length":7,"data":"Самара"},{"type":"hashtag","offset":73,"length":5,"data":"офис"},{"type":"hashtag","offset":79,"length":16,"data":"полнаязанятость"},{"type":"handle","offset":1193,"length":13,"data":"bogdanova_hr"},{"type":"link","offset":1229,"length":21,"data":"mailto:nsboykova@sberbank.ru"}],"date":"2020-06-18T16:34:47+00:00","link":"tg://resolve?domain=qa_jobs&post=0","tags":[{"name":"qa"},{"name":"hadoop"},{"name":"sql"},{"name":"jenkins"},{"name":"excel"},{"name":"hive"}],"cities":[{"code":"samara"}],"allowsRemote":false}},{"node":{"__typename":"Job","id":"103155761152-1001089317451","title":"Qa инженер","text":"#вакансия #москва #полнаязанятость #мегафон #bigdata #покаработаемиздомапотомвофис\n\nМы ищем QA-инженера в команду для тестирования внутренних и внешних сервисов.\n\nЧем предстоит заниматься:\n\n- Разработка модулей интеграционных тестов для наших сервисов;\n- Подготовка тестовых данных (работа с hive/oracle);\nРабота с SQL/HiveQL (Oracle/Hive);\n- Написание алгоритмов работы с данными, в рамках тестирования;\n- Взаимодействие с разработчиками и аналитиками в процессе проектирования и развития;\n- Выявление, фиксация и контроль багов в баг-трекере (Jira);\n- Ведение документации по тестированию (confluence);\n\nИспользуемые технологии:\nДля разработки – Play, Spring, Flask, Scala, Java (8+), Python(3+);\nДля тестирования: Java/Scala & Maven + TestNG + Google Guice;\nДля работы сервисов – Docker;\nДля работы с кодом – GitLab;\nДля работы с задачами – Jira.\n\nМы ожидаем от вас:\n- Опыт работы в автоматизации тестирования от 1 года;\n- Знание структур данных и алгоритмов;\n- Уверенное знание Java;\n- Уверенное знание фреймворков TestNG/JUnit;\n- Опыт работы в автоматизации тестирования;\n- Опыт работы с реляционными СУБД (Oracle/PostgreSQL);\n- Умение писать хорошо читаемый код;\n- Умение работать с VCS (Git) и сборщиками (maven).\n\nБудет плюсом:\n- Опыт в области тестирования приложений по работе с большими данными;\n- Опыт в нагрузочном тестировании;\n- Опыт работы с Spring/Google Guice;\n- Опыт конфигурирования CI/CD (GitLab);\n- Умение писать код на Scala;\n- Опыт работы с Hadoop/Spark.\n\nЧто мы предлагаем:\n- Внутреннее и внешнее обучение в России (Coursera, New Prolab, Geek Brains и др.);\n- Новый офис в центре: 7 минут пешком от м. Маяковская/Новослободская;\n- Компенсация затрат на мобильную связь;\nДМС (включая стоматологию);\n- Частичная компенсация спорта;\n- Возможность участия в корпоративных спортивных командах: футбол, волейбол, баскетбол, хоккей и бег\n- Регулярные митапы в офисе с внешними спикерами из разных областей.\n\n#мегафон #bigdata\nКонтакты: Svetlana.stakanova@megafon.ru или @svetastakanova","markup":[{"type":"hashtag","offset":0,"length":9,"data":"вакансия"},{"type":"hashtag","offset":10,"length":7,"data":"москва"},{"type":"hashtag","offset":18,"length":16,"data":"полнаязанятость"},{"type":"hashtag","offset":35,"length":8,"data":"мегафон"},{"type":"hashtag","offset":44,"length":8,"data":"bigdata"},{"type":"hashtag","offset":53,"length":29,"data":"покаработаемиздомапотомвофис"},{"type":"hashtag","offset":1926,"length":8,"data":"мегафон"},{"type":"hashtag","offset":1935,"length":8,"data":"bigdata"},{"type":"link","offset":1954,"length":29,"data":"mailto:Svetlana.stakanova@megafon.ru"},{"type":"handle","offset":1988,"length":15,"data":"svetastakanova"}],"date":"2020-06-18T09:58:49+00:00","link":"tg://resolve?domain=qa_jobs&post=0","tags":[{"name":"qa"},{"name":"hive"},{"name":"oracle"},{"name":"sql"},{"name":"playframework"},{"name":"spring"},{"name":"flask"},{"name":"scala"},{"name":"java"},{"name":"python"},{"name":"maven"},{"name":"docker"},{"name":"gitlab"},{"name":"junit"},{"name":"postgresql"},{"name":"git"},{"name":"hadoop"}],"cities":[{"code":"moscow"}],"allowsRemote":false}}]}}},"context":{}}