{"hash":"f5f6bf98bd95e769321482904cbbd488f77922fd","data":{"records":{"id":"sql","name":"sql","belongsTo":{"totalCount":169,"pageInfo":{"totalPages":17,"currentPage":2},"edges":[{"node":{"__typename":"Job","id":"104201191424-1001089317451","title":"Qa инженер","text":"#вакансия #QA #Java #QAAutomation #Москва #офис \n\nВакансия: QA Lead (Тест-Менеджер)\nГород: Москва м. Технопарк \nЗарплата: от 250 000 рублей до 290 000 рублей на руки\nФормат: офис, полный день, полная занятость\nКомпания Innovative People \n\n🕘 Чем предстоит заниматься:\n• планирование тестирования;\n• выстраивание процессов тестирования среди 8 команд с упором на автоматизацию;\n• выстраивать CI/CD проекта;\n• налаживание взаимодействия QA инженеров в нескольких командах;\n• поддерживать и развивать разработанные решения по автоматизации;\n• исследовать новые технологии и внедрять их на проекте;\n• принятие решений о внедрении / обновлении программного обеспечения.\n\n🕒 От кандидата ожидаем:\n• опыт в тестировании от 4х лет\n• опыт в автотестировании от 3х лет\n• опыт руководства группой тестировщиков от 2х лет\n• практический опыт применения практик тест-дизайна\n• умение проектировать тест-кейсы и подготавливать тестовые данные для тестирования\n• хорошие знание Java, библиотек\n• уверенное использование и понимание как работает под капотом Selenium Webdriver (Selenide и Appium для мобильных платформ)\n• опыт написания собственного фреймворка\n• опыт работы в unix системах\n• опыт работы с API (Soap, Rest)\n• опыт использование git\n• опыт использование CI (желательно, но не обязательно Jenkins)\n• опыт работы с Docker\n• опыт составления запросов SQL\n• опыт управления непрямыми (функциональными) подчиненными\n• умение контролировать несколько проектов одновременно\n• умение мотивировать команду, опыт управления рисками, мониторинг эффективности процессов\n\n🕧 Предлагаем:\n• все по ТК РФ\n• ДМС со стоматологией, программа лояльности\n• Macbook \n• адекватное руководство и лояльные процессы\n• большое комьюнити, классные команды\n• помогаем с релокацией!\n\nРезюме и вопросы @Priboch","markup":[{"type":"hashtag","offset":0,"length":9,"data":"вакансия"},{"type":"hashtag","offset":10,"length":3,"data":"QA"},{"type":"hashtag","offset":14,"length":5,"data":"Java"},{"type":"hashtag","offset":20,"length":13,"data":"QAAutomation"},{"type":"hashtag","offset":34,"length":7,"data":"Москва"},{"type":"hashtag","offset":42,"length":5,"data":"офис"},{"type":"handle","offset":1771,"length":8,"data":"Priboch"}],"date":"2020-07-02T09:23:09+00:00","link":"tg://resolve?domain=qa_jobs&post=99374","tags":[{"name":"qa"},{"name":"java"},{"name":"selenium"},{"name":"unix"},{"name":"soap"},{"name":"rest"},{"name":"git"},{"name":"jenkins"},{"name":"docker"},{"name":"sql"}],"cities":[{"code":"moscow"}],"allowsRemote":false}},{"node":{"__typename":"Job","id":"104180219904-1001089317451","title":"Qa engineer","text":"#Москва  #QA  #вакансия #офис\nКомпания: Start.ru\n\nМы ищем коллег, которые смогут влиться в нашу команду и вместе с нами развивать и совершенствовать наш сервис!\nУ Вас есть возможность стать частью команды, развивающей первую в Восточной Европе студию с собственным международным VOD сервисом.\nВ данный момент мы усиляем нашу команду по тестированию и в поисках позиций Backend QA Engineer и QA Automation Engineer (python)\n\n———————————\nДолжность: Backend QA Engineer\nЗарплатная вилка: От 80.р. до 120т.р. по результатам собеседования\n\nКакие задачи вы будете решать:\n- Прогон описаных кейсов в TestRail и документация найденых дефектов;\n- Тестирование API (программного интерфейса платформы);\n- Разработка тестовых сценариев;\n- Взаимодействие с разработчиками и сопровождение дефектов до полного их решения;\n- Отладка и сбор логов в процессе воспроизведения проблем\n- Проведение регрессионного тестирования\n\nЧего мы хотим:\n- Вас не пугает работа с командной строкой чаще чем работа с графическим интерфейсом\n- Работа с chromedev tools и командной строкой (bash);\n- Знание и понимания клиент-серверной архитектуры приложений;\n- Понимание принципов работы веб-приложений;\n- Умение грамотно составлять свои мысли в предложения и описывать дефекты, чтобы понятно было разработчикам;\n- Навыки работы с технической документацией, анализ и вычленение требований;\n- Работали с программами-снифферами и проксями траффика (charles/wireshark/fiddler/mitmproxy etc)\n\nБудет плюсом:\n- Если знаете python на уровне, достаточном для автоматизации и сможете прочитать код который на нем написан\n- Знаете что такое DOM-дерево, локаторы и селекторы в контексте веб-приложения\n\n—————————\nДолжность: QA Automation Engineer\nЗарплатная вилка: От 130.р. до 170т.р. по результатам собеседования\n\nУ нас:\nВ нашем проекте есть автоматизация тестирования как API, так и WEB UI. \nНаш стек: Python3, PyTest, Requests, Selenium WebDriver, Selenoid, DB clients (MongoDB, PostgreSQL), JSON validation (jsonschema), TestRail API, Telegram API, GitLab CI. \nПомимо автотестов мы разрабатываем проект нагрузочного тестирования на Locust.\n\nВаши задачи:\n- Расширение покрытия автотестов API, WEB UI\n- Поддержка автотестов в актуальном состоянии\n- Анализ прохождения тестов с возможным заведением багов в Jira\n- Ревью кода\n- Ведение тестовой - документации\n- Написание сценариев нагрузочного тестирования\n\nТребования:\n- Хорошее знание теории тестирования\n- Опыт автоматизированного тестирования от 2х лет\n- Знание Python3, PyTest\n- Навыки написания и использования тестовой документации\n- Умение писать простые запросы на SQL и в MongoDB\n- Навыки работы с Git\n- Обсуждение проблем приложения с разработчиками\n\nБудет плюсом:\n- Опыт написания архитектуры проекта автотестов с нуля\n- Работа с Docker, Docker Compose\n- Опыт работы с Telegram API\n- Опыт описания JSON схем для валидации ответов API\n- Базовые знания в Linux\n\nОт нас:\n- На данный момент условия сотрудничества удаленные, но при нормализации ситуации мы выйдем в офис\n- Офис в районе Хамовники (территориально м.Киевская, м. Спортивная в 20.мин ходьбы)\n- График работы: 5/2 начинаем с 9  до 11 (в целом гибкий - главное результат);\n- Оформление в соответствии с ТК РФ (белая зарплата, отпускные, больничные);\n- Все возможности для прокачки имеющихся скиллов и получения новых;\n- Драйвовая и высокопрофессиональная команда единомышленников;\n- Возможность стать частью динамично развивающегося видеосервиса.\n\n\nВопросы и отклики по вакансии писать в tlgrm: @unambo OR emailto: v.selyanin@start.ru","markup":[{"type":"hashtag","offset":0,"length":7,"data":"Москва"},{"type":"hashtag","offset":9,"length":3,"data":"QA"},{"type":"hashtag","offset":14,"length":9,"data":"вакансия"},{"type":"hashtag","offset":24,"length":5,"data":"офис"},{"type":"link","offset":40,"length":8,"data":"http://Start.ru"},{"type":"handle","offset":3471,"length":7,"data":"unambo"},{"type":"link","offset":3491,"length":19,"data":"mailto:v.selyanin@start.ru"}],"date":"2020-07-02T07:33:55+00:00","link":"tg://resolve?domain=qa_jobs&post=99354","tags":[{"name":"qa"},{"name":"python"},{"name":"bash"},{"name":"web"},{"name":"selenium"},{"name":"mongodb"},{"name":"postgresql"},{"name":"json"},{"name":"gitlab"},{"name":"sql"},{"name":"git"},{"name":"docker"},{"name":"linux"},{"name":"docker-compose"}],"cities":[{"code":"moscow"},{"code":"kiev"}],"allowsRemote":false}},{"node":{"__typename":"Job","id":"72512176128-1001054966032","title":"Android разработчик","text":"#вакансия #работа #Android #Kotlin#JavaCore #удаленка\n\nФормат работы: фулл тайм удаленно \nЗанятость: полная\nЗарплатная вилка: от 130 000 до 170 000\nВакансия: Android-разработчик\nПодробности:@Jane1204\n\nRaxel Telematics - это международная компания, базирующаяся в Сингапуре, которая занимается сбором и анализом телематических данных с мобильных устройств, в данный момент находится в поиске кандидата на роль Android разработчика (удаленно).\n\nЧем предстоит заниматься:\n-Осуществлять разработку основных модулей и интерфейсов в мобильных приложениях в соответствии с заданиями от руководителя команды разработки;\n-Осуществлять разработку внутренних модулей и библиотек по сбору данных пользователя и передаче статистики;\n-Вести документацию разрабатываемого программного обеспечения;\n-Вести список задачи и поддерживать актуальным статус задач в системе Jira;\n-Формировать задания группе тестирования в проверке работоспособности мобильного программного обеспечения.\n\nЧто ожидаем мы:\n-Знание Android SDK, Java Core, Kotlin;\n-Знание и понимание принципов ООП, структур данных и классических алгоритмов;\n-Понимание REST API;\n-Понимание принципов Material Design;\n-Понимание принципов Android Clean Architecture, MVP, DI;\n-Знание SQL/SQLite;\n-Умение использовать в работе rxjava/rxjava2, retrofit2, dagger2, picasso, otto и др.;\n-Умение писать качественный код;\n-Понимание и использование принципов SOLID\n\nЧто предлагаем мы:\n-Работу в молодой амбициозной команде с возможностью обучения и дальнейшего профессионального развития\n-Международный опыт работы с иностранными коллегами и клиентами\n-Новые и интересные задачи с использованием современного стэка технологий\n-от 130 000 до 170 000 руб. на руки\n-Удаленная работа full-time (по желанию есть офис в центре МСК, но почти вся команда работает удаленно)\n\nКонтакты: \nTelegram: @Jane1204\nEmail: manuylovaey@gmail.com\nЕвгения","markup":[{"type":"hashtag","offset":0,"length":9,"data":"вакансия"},{"type":"hashtag","offset":10,"length":7,"data":"работа"},{"type":"hashtag","offset":18,"length":8,"data":"Android"},{"type":"hashtag","offset":44,"length":9,"data":"удаленка"},{"type":"handle","offset":190,"length":9,"data":"Jane1204"},{"type":"handle","offset":1824,"length":9,"data":"Jane1204"},{"type":"link","offset":1841,"length":21,"data":"mailto:manuylovaey@gmail.com"}],"date":"2020-07-02T07:28:48+00:00","link":"tg://resolve?domain=mobile_jobs&post=69153","tags":[{"name":"mobile"},{"name":"android"},{"name":"kotlin"},{"name":"java"},{"name":"rest"},{"name":"sql"},{"name":"sqlite"}],"cities":[],"allowsRemote":true}},{"node":{"__typename":"Job","id":"104170782720-1001089317451","title":"Qa инженер","text":"🐞🐞🐞#вакансия #QA #Ульяновск #Саранск #Казань #Самара #Уфа #Краснодар #офис #удаленная_работа\n\n🔍Middle QA-специалист🔎\n\n⚡️Компания: Simbirsoft (более 19 лет на рынке, более 700 сотрудников в штате)\n\nОчень ждем тебя, наш будущий коллега и борец за качественное ПО! ☺️\n\n📌Твои будущие задачи:\n• тестирование ПО (frontend, backend, API);\n• локализация и документирование найденных дефектов;\n• ведение и оптимизация тестовой документации;\n• контроль качества на всех этапах разработки ПО;\n• выстраивание и оптимизация процессов тестирования ПО.\n\n📌Что мы ждем от тебя:\n• наличие опыта от 2 лет в направлениях QA или тестирования ПО;\n• понимание разницы между QA и тестированием ПО;\n• понимание особенностей гибких методологий;\n• уверенное владение техниками тест-дизайна;\n• знание клиент-серверной архитектуры;\n• понимание особенностей тестирования web, mobile и desktop приложений;\n• навык тестирования API;\n• написание запросов SQL;\n• опыт работы с системами контроля версий (git);\n• знание основных команд работы с консолью (Windows/Linux).\n\n📌Что мы предлагаем:\n• Полностью белая ЗП два раза в месяц;\n• Оформление по ТК РФ;\n• Высокий уровень экспертности внутри компании, которым мы делимся друг с другом;\n• Перспективы вертикального и горизонтального роста;\n• Работа на российских и международных проектах;\n• Оборудованное рабочее место и парк тестовых устройств;\n• Подготовка и прохождение сертификации ISTQB бесплатно;\n• Внутренние и внешние курсы, доклады, конференции;\n• Бесплатные чай, кофе, печеньки в офисе;\n• Корпоративная спортивная программа (оплата тематических секций, частичная компенсация абонемента);\n• Проведение летних и зимних корпоративов, дня именинника, совместные походы и т.д.\n\n📌Зарплата:\n• от 50 000 (Договорная, по итогу собеседования)\n\n☎️Контакты: @julia_kli","markup":[{"type":"hashtag","offset":6,"length":9,"data":"вакансия"},{"type":"hashtag","offset":16,"length":3,"data":"QA"},{"type":"hashtag","offset":20,"length":10,"data":"Ульяновск"},{"type":"hashtag","offset":31,"length":8,"data":"Саранск"},{"type":"hashtag","offset":40,"length":7,"data":"Казань"},{"type":"hashtag","offset":48,"length":7,"data":"Самара"},{"type":"hashtag","offset":56,"length":4,"data":"Уфа"},{"type":"hashtag","offset":61,"length":10,"data":"Краснодар"},{"type":"hashtag","offset":72,"length":5,"data":"офис"},{"type":"hashtag","offset":78,"length":17,"data":"удаленная_работа"},{"type":"handle","offset":1779,"length":10,"data":"julia_kli"}],"date":"2020-07-02T06:05:28+00:00","link":"tg://resolve?domain=qa_jobs&post=99345","tags":[{"name":"qa"},{"name":"web"},{"name":"mobile"},{"name":"sql"},{"name":"git"},{"name":"windows"},{"name":"linux"}],"cities":[{"code":"ulyanovsk"},{"code":"saransk"},{"code":"kazan"},{"code":"samara"},{"code":"ufa"},{"code":"krasnodar"}],"allowsRemote":true}},{"node":{"__typename":"Job","id":"26941063168-1001075660570","title":"Php разработчик","text":"#вакансия #laravel #удалёнка #удаленно #ищем\n\nПривет мир!\n\nМы ищем backend-разработчика (Laravel) в небольшую продуктовую команду, которая в данный момент разрабатывает MVP для SaaS продукта (продажа услуг в интернете).\n\nВ твои обязанности будет входить разработка API, внутренней админки, а также интеграция с платежными системами.\n\nУ нас также имеются рабочие проекты, в будущем можно будет перейти на один из них при желании.\n\n🔧 Требования:\n— Опыт разработки не менее 3 лет;\n— Отличное знание PHP (понимание сильных и слабых сторон);\n— Знание SQL и умение проектировать базы данных;\n\n👀 Плюсами будет:\n— Опыт коммерческой разработки\n— Опыт работы с обработкой платежей и внутренними балансами, понимание того, как делать НЕ надо.\n— Опыт настройки CI/CD пайплайнов\n— Базовое понимание как работает фронтенд (в частности React / SSR), и как это влияет на проектирование API.\n— Опыт работы с Node.JS\n— Умение думать не только про код, но и про продукт.\n\n⭐️  Почему мы?\n— Возможность повлиять на технологический стек на раннем этапе;\n— Свободный график;\n— Возможность роста в желаемом для тебя направлении;\n— ЗП два раза в месяц;\n\n💰 Зарплата\nот 80 000 до 100 000 руб. (супер сильным кандидатам готовы дать больше)\n\nСвязь и резюме: @l3v1k","markup":[{"type":"hashtag","offset":0,"length":9,"data":"вакансия"},{"type":"hashtag","offset":10,"length":8,"data":"laravel"},{"type":"hashtag","offset":19,"length":9,"data":"удалёнка"},{"type":"hashtag","offset":29,"length":9,"data":"удаленно"},{"type":"hashtag","offset":39,"length":5,"data":"ищем"},{"type":"bold","offset":67,"length":20,"data":""},{"type":"handle","offset":1232,"length":6,"data":"l3v1k"}],"date":"2020-07-01T20:41:53+00:00","link":"tg://resolve?domain=php_jobs&post=25693","tags":[{"name":"php"},{"name":"laravel"},{"name":"sql"},{"name":"reactjs"},{"name":"nodejs"}],"cities":[],"allowsRemote":true}},{"node":{"__typename":"Job","id":"26927431680-1001075660570","title":"Php разработчик","text":"#php #вакансия #удалёнка \n\nPHP Engineer\nФормат работы: #fulltime #remote\nЗарплата: $ 40 000 - 50 000 в год\nГород: удаленно\n\nНебольшая, но быстро растущая студия разработки из Лондона ищет PHP-ниндзю. На нашем счету много успешных проектов, большая часть которых — британские. \n\nТребования:\n— Опыт в разработке не менее 3 лет;\n— Знание PHP как родного,\n— Знание SQL, особенно MySQL или PostgreSQL \n— Понимание HTML/CSS;\n— Быть знакомым с PHP MVC Framework, JavaScript (and jQuery);\n— Опыт в Version Control (Git);\n— Опыт с Bash and Unix (обычно мы используем Ubuntu 16.04) \n— Уровень английского С2;\n— Опыт с алгоритмами приветствуется;\n— Большим плюсом будет знание Laravel (или хотя бы Symfony), фреймворки CakePHP, Zend, CodeIgniter тоже ок, но все равно потребуется освоить Laravel.\n\nЧтобы откликнуться, необходимо пройти короткий отбор по ссылке https://6nomads.com/ (обязательное условие найма🤷‍♀️)\n\nКонтакт для связи @temnik_sofya","markup":[{"type":"hashtag","offset":0,"length":4,"data":"php"},{"type":"hashtag","offset":5,"length":9,"data":"вакансия"},{"type":"hashtag","offset":15,"length":9,"data":"удалёнка"},{"type":"hashtag","offset":55,"length":9,"data":"fulltime"},{"type":"hashtag","offset":65,"length":7,"data":"remote"},{"type":"link","offset":85,"length":15,"data":"tel:40 000 - 50 000"},{"type":"link","offset":850,"length":20,"data":"https://6nomads.com/"},{"type":"handle","offset":924,"length":13,"data":"temnik_sofya"}],"date":"2020-07-01T17:36:31+00:00","link":"tg://resolve?domain=php_jobs&post=25680","tags":[{"name":"php"},{"name":"sql"},{"name":"mysql"},{"name":"postgresql"},{"name":"html"},{"name":"css"},{"name":"javascript"},{"name":"jquery"},{"name":"git"},{"name":"bash"},{"name":"unix"},{"name":"ubuntu"},{"name":"laravel"},{"name":"symfony"},{"name":"cakephp"},{"name":"zend-framework"},{"name":"codeigniter"}],"cities":[],"allowsRemote":true}},{"node":{"__typename":"Job","id":"26920091648-1001075660570","title":"Php developer","text":"#вакансия #удаленно #php\n\nСтабильная растущая IT компания (не стартап) ищет в свою ламповую команду Middle/Senior Backend PHP Developer (или Fullstack с уклоном в Backend) на fulltime.\n\nКлючевые навыки:\n– SQL (PostgreSQL),\n– PHP 7,\n– Symfony 2,\n– умение ориентироваться в базах данных и их проектировании,\n– умение преобразовывать техническое задание в план работ.\n\nБудет плюсом:\n– MySQL,\n– MSSQL,\n– PHP 5,\n– опыт оценки временных затрат на выполнение задач.\n\nСтек технологий:\n– PHP 7.2,\n– PostgreSQL,\n– JS,\n– Bootstrap,\n– Symfony 2.\n\nОт нас:\n– удалённая работа,\n– свободный график,\n– гибкость в профессиональном росте,\n– ламповое общение внутри команды,\n– возможность переключения между проектами,\n– сложные и интересные задачи,\n– поддержка в развитии профессиональных навыков и обучении перспективным для проектов технологиям,\n– возможность влиять на стек технологий проектов,\n– зарплатная вилка в зависимости от прохождения собеседования $12 - $15 в час,\n– полная занятость.\n\nКратко о нас:\n– компания с выстроенным процессом управления, коммуникацией и delivery,\n– специализация: бизнес анализ, развитие, модернизация и поддержка авторских приложений,\n– мы более 10 лет на рынке IT США и Европы,\n– проекты с надёжными заказчиками,\n– русскоязычная команда, которая любит своё дело,\n– основное направление работы – развитие, модернизация и поддержка авторского web-приложения.\n\nЖдём твоего резюме на career@tomita.pro!","markup":[{"type":"hashtag","offset":0,"length":9,"data":"вакансия"},{"type":"hashtag","offset":10,"length":9,"data":"удаленно"},{"type":"hashtag","offset":20,"length":4,"data":"php"},{"type":"link","offset":1401,"length":17,"data":"mailto:career@tomita.pro"}],"date":"2020-07-01T15:47:46+00:00","link":"tg://resolve?domain=php_jobs&post=25673","tags":[{"name":"php"},{"name":"sql"},{"name":"postgresql"},{"name":"symfony"},{"name":"mysql"},{"name":"sql-server"},{"name":"bootstrap"},{"name":"web"}],"cities":[],"allowsRemote":true}},{"node":{"__typename":"Job","id":"104141422592-1001089317451","title":"Qa engineer","text":"#вакансия #Саратов #fulltime #офис #QA \n\nВсем привет! Компания \"Проектная команда\". Расширяем штат и ищем человека с ответственным подходом к работе и желанием роста. Работа с долгосрочным проектом, по тестированию Банковского ПО.\n\nДолжность- manual QA Engineer;\n\nТребуемый опыт работы: от 1,5 года;\n\nПолная занятость, полный день.\n\nОбязанности:\n\n-Ручное тестирование.\n\n- Выявление, анализ ошибок и проблем;\n\n- Документирование найденных дефектов.\n\nТребования:\n\n- Высшее техническое образование/cтаршие курсы технического ВУЗа (желательно);\n\n\n- Понимание методологии разработки программного обеспечения;\n\n- Знание XML, XSD, веб-сервисах;\n\n- Знание SQL;\n\n- Владение инструментами: Postman, Git, SoapUI;\n\n- Умение работать с системами учета дефектов (Jira);\n\n- Опыт работы с bug tracking и task tracking системами;\n\n- Активная позиция, желание развиваться в области функционального тестирования.\n\nУсловия:\n\n- Удобный хорошо оборудованный офис;\n\n- Официальное трудоустройство;\n\n- «Белая» заработная плата;\n\n- ДМС со стоматологией (после года работы);\n\n- Дополнительные бонусы по результатам года;\n\n- Заработная плата по результатам собеседования от 40000-85000 (на руки);\n\nМожно откликнуться на hh.ru/vacancy/37402257\nИли на почту: Shkonda_ag@creativesoftlab.ru\nТак же- пишите в лс.","markup":[{"type":"hashtag","offset":0,"length":9,"data":"вакансия"},{"type":"hashtag","offset":10,"length":8,"data":"Саратов"},{"type":"hashtag","offset":19,"length":9,"data":"fulltime"},{"type":"hashtag","offset":29,"length":5,"data":"офис"},{"type":"hashtag","offset":35,"length":3,"data":"QA"},{"type":"link","offset":1146,"length":11,"data":"tel:40000-85000"},{"type":"link","offset":1192,"length":22,"data":"http://hh.ru/vacancy/37402257"},{"type":"link","offset":1229,"length":29,"data":"mailto:Shkonda_ag@creativesoftlab.ru"}],"date":"2020-07-01T14:37:01+00:00","link":"tg://resolve?domain=qa_jobs&post=99317","tags":[{"name":"qa"},{"name":"xml"},{"name":"xsd"},{"name":"sql"},{"name":"git"}],"cities":[{"code":"saratov"}],"allowsRemote":false}},{"node":{"__typename":"Job","id":"104120451072-1001089317451","title":"Qa инженер","text":"#вакансия #middle #офис #fulltime #Москва \n\nВсем привет!\nВ связи с ростом проектов открыта вакансия Специалиста по тестированию/ QC в международную продуктовую финтех компанию CMA. Занимаются разработкой платежных систем, работающих на национальных масштабах.\n\nСейчас их решениями пользуются более 40-ка компаний в России (ВТБ24, Банк России, Московская Биржа и т.д.) и более 100 клиентов и за рубежом.\n\nЧем предстоит заниматься:\n- Практическое применение методик тест-дизайна и анализа тестового покрытия;\n- Проведение ручного тестирования (50%) и участие в разработке автоматизированных тестов (50%);\n- Анализ проектной документации, разработка тест-кейсов, чек-листов;\n- Анализ и заведение багов в Jira.\nЧто хотели бы видеть в профиле кандидата:\n- Опыт написания авто-тестов ( Java, Java Script, XSLT, HTML) + работа с фрэймворком для автоматизации тестирования ;\n- Знание основ SQL(на уровне простых запросов), практика работы с XML;\n- Опыт работы с программными продуктами: Oracle Database, VirtualBox, Jira, Confluence, Git, Toad, WireShark, багтрекерами или ALM системами (JIRA, HP ALM и другие).\nЧто готовы предложить:\n- Заработная плата от 100 000 net;\n- Гибкое начало рабочего дня;\n- Офис на станции метро Динамо, бесплатный автобус до БЦ;\n- Наличие свободных парковочных мест рядом с БЦ;\n- Оплата обедов;\n- Страхование жизни и для поездок за пределы РФ.\n\nЕсли вакансия заинтересовала, можете откликаться на HH: https://hh.ru/vacancy/37770841\nИли пишите в ЛС @astarichkova","markup":[{"type":"hashtag","offset":0,"length":9,"data":"вакансия"},{"type":"hashtag","offset":10,"length":7,"data":"middle"},{"type":"hashtag","offset":18,"length":5,"data":"офис"},{"type":"hashtag","offset":24,"length":9,"data":"fulltime"},{"type":"hashtag","offset":34,"length":7,"data":"Москва"},{"type":"bold","offset":100,"length":31,"data":""},{"type":"bold","offset":176,"length":3,"data":""},{"type":"bold","offset":404,"length":26,"data":""},{"type":"bold","offset":707,"length":42,"data":""},{"type":"bold","offset":1104,"length":23,"data":""},{"type":"italic","offset":1366,"length":116,"data":""},{"type":"link","offset":1422,"length":30,"data":"https://hh.ru/vacancy/37770841"},{"type":"handle","offset":1469,"length":13,"data":"astarichkova"}],"date":"2020-07-01T08:46:53+00:00","link":"tg://resolve?domain=qa_jobs&post=99297","tags":[{"name":"qa"},{"name":"java"},{"name":"xslt"},{"name":"html"},{"name":"sql"},{"name":"xml"},{"name":"oracle"},{"name":"git"},{"name":"dotnet"}],"cities":[{"code":"moscow"}],"allowsRemote":false}},{"node":{"__typename":"Job","id":"17277386752-1001110946746","title":"Js разработчик","text":"#вакансия #вакансии #удаленная #работа #разработчик #remote #job #remotejob #full #stack #fullstack #software #engineer #develop #developer #node #react #amazon #aws #api #crm #erp #zoho #us #usa\n\n😎 Full Stack Software Engineer\n\nКомпания: Deep Consulting Solutions (Austin, Texas)\n\nМестоположение: Anywhere\n\nФормат работы: Remote \n\nЗанятость: Full Time, Flexible Schedule \n\nЗарплата: $20-80K в год. Compensation plan depends on level of ability, responsibility taken, and results delivered. Compensation consists of base and bonus pay.\n \nОписание вакансии:\n\nhttps://zfrmz.com/yIDN35yaj3apxsNfR9qS?src=irina-itrecruiter\n\nRequirements:\n\nYou must be:\n\n- A mature and responsible individual driven by results and not activities.\n- An individual with genuine interest in technology.\n- Willing to learn, grow, and admit mistakes.\n- Able to communicate with other people on the project's team effectively.\n \nSkills/Experience:\n\n- Node.js, React, SQL and NoSQL databases.\n- APIs.\n- Effective Written and Verbal English.\n- Basic Understanding of DevOps and SDLC.\n \nThe following will be a good plus:\n\n- Experience with Amazon AWS, serverless technologies, and microservices on its platform.\n- Experience with CRM and ERP systems such as Zoho and others.\n\nКак подать заявку:\n\nhttps://zfrmz.com/yIDN35yaj3apxsNfR9qS?src=irina-itrecruiter\n\nКонтакт:\n@Aagdan","markup":[{"type":"hashtag","offset":0,"length":9,"data":"вакансия"},{"type":"hashtag","offset":10,"length":9,"data":"вакансии"},{"type":"hashtag","offset":20,"length":10,"data":"удаленная"},{"type":"hashtag","offset":31,"length":7,"data":"работа"},{"type":"hashtag","offset":39,"length":12,"data":"разработчик"},{"type":"hashtag","offset":52,"length":7,"data":"remote"},{"type":"hashtag","offset":60,"length":4,"data":"job"},{"type":"hashtag","offset":65,"length":10,"data":"remotejob"},{"type":"hashtag","offset":76,"length":5,"data":"full"},{"type":"hashtag","offset":82,"length":6,"data":"stack"},{"type":"hashtag","offset":89,"length":10,"data":"fullstack"},{"type":"hashtag","offset":100,"length":9,"data":"software"},{"type":"hashtag","offset":110,"length":9,"data":"engineer"},{"type":"hashtag","offset":120,"length":8,"data":"develop"},{"type":"hashtag","offset":129,"length":10,"data":"developer"},{"type":"hashtag","offset":140,"length":5,"data":"node"},{"type":"hashtag","offset":146,"length":6,"data":"react"},{"type":"hashtag","offset":153,"length":7,"data":"amazon"},{"type":"hashtag","offset":161,"length":4,"data":"aws"},{"type":"hashtag","offset":166,"length":4,"data":"api"},{"type":"hashtag","offset":171,"length":4,"data":"crm"},{"type":"hashtag","offset":176,"length":4,"data":"erp"},{"type":"hashtag","offset":181,"length":5,"data":"zoho"},{"type":"hashtag","offset":187,"length":3,"data":"us"},{"type":"hashtag","offset":191,"length":4,"data":"usa"},{"type":"link","offset":559,"length":60,"data":"https://zfrmz.com/yIDN35yaj3apxsNfR9qS?src=irina-itrecruiter"},{"type":"link","offset":1267,"length":60,"data":"https://zfrmz.com/yIDN35yaj3apxsNfR9qS?src=irina-itrecruiter"},{"type":"handle","offset":1338,"length":7,"data":"Aagdan"}],"date":"2020-07-01T05:19:22+00:00","link":"tg://resolve?domain=javascript_jobs_feed&post=16477","tags":[{"name":"javascript"},{"name":"nodejs"},{"name":"reactjs"},{"name":"amazon-web-services"},{"name":"sql"},{"name":"nosql"}],"cities":[{"code":"austin"}],"allowsRemote":true}}]}}},"context":{}}