{"hash":"f5f6bf98bd95e769321482904cbbd488f77922fd","data":{"entry":{"id":"72550973440-1001054966032","title":"Ios разработчик","text":"#вакансия #ios #swift #москва #офис #objectivec\n\nГород: Москва (ст.м. Аэропорт).\n\nФормат работы: full-time.\n\nЗанятость: полная. \n\nВилка: 100-200 т.р. на руки.\n\nФункционал:\n\n• Разработка мобильных приложений под платформу iOS.\n\n• Участие в командной разработке, тестировании, оптимизации существующих мобильных приложений на платформе iOS \n\nПрофессиональные знания: \n\nОтличное знание Objective-C/Swift, iOS SDK 10+;\nОпыт разработки мобильных приложений - от 2 лет;\nЗнание шаблонов проектирования, принципы SOLID, умение их применять;\nЗнакомы с основными алгоритмами и структурами данных;\nУмение работать со Storyboard и Autolayout;\nОпыт разработки клиент-серверных приложений, понимание принципов и устройства сетевого взаимодействия (HTTPS, JSON, REST);\nУмеете работать в команде и конструктивно реагируете на аргументы коллег;\nУмение разбираться и работать с чужим кодом;\nЗнание распределенных систем контроля версий (Git). \n\nНазвание компании: Локо-Банк\nhttps://www.lockobank.ru//\nhttps://hh.ru/vacancy/37365811\n\nКонтакты: @hrlocko","markup":[{"type":"hashtag","offset":0,"length":9,"data":"вакансия"},{"type":"hashtag","offset":10,"length":4,"data":"ios"},{"type":"hashtag","offset":15,"length":6,"data":"swift"},{"type":"hashtag","offset":22,"length":7,"data":"москва"},{"type":"hashtag","offset":30,"length":5,"data":"офис"},{"type":"hashtag","offset":36,"length":11,"data":"objectivec"},{"type":"link","offset":956,"length":26,"data":"https://www.lockobank.ru//"},{"type":"link","offset":983,"length":30,"data":"https://hh.ru/vacancy/37365811"},{"type":"handle","offset":1025,"length":8,"data":"hrlocko"}],"date":"2020-07-02T13:41:35+00:00","link":"tg://resolve?domain=mobile_jobs&post=69190","tags":[{"name":"mobile"},{"name":"ios"},{"name":"swift"},{"name":"objective-c"},{"name":"json"},{"name":"rest"},{"name":"git"}],"cities":[{"code":"moscow","ruName":"Москва","enName":"Moscow","country":{"code":"russia","ruName":"Россия","enName":"Russia"}}],"allowsRemote":false}},"context":{"recordId":"72550973440-1001054966032"}}